MANIFEST.in
setup.py
friendlists/__init__.py
friendlists/config.py
friendlists.egg-info/PKG-INFO
friendlists.egg-info/SOURCES.txt
friendlists.egg-info/dependency_links.txt
friendlists.egg-info/not-zip-safe
friendlists.egg-info/requires.txt
friendlists.egg-info/top_level.txt
friendlists/static/css/normalize.css
friendlists/static/css/styles.css
friendlists/templates/app.html
friendlists/templates/base.html
friendlists/templates/index.html